{"stem":"029","instances":[{"docId":"toc","docUri":"toc.html","score":2,"contexts":[{"form":"029","weight":"1","pos":1142,"context":"Anonymus <mark>029<\/mark>","fid":"tocTable"},{"form":"029","weight":"1","pos":1144,"context":"anonymus-<mark>029<\/mark>.xml","fid":"tocTable"}]},{"docId":"anonymus-029","docUri":"anonymus-029.html","score":3,"contexts":[{"form":"029","weight":"2","pos":14,"context":"Anonymus <mark>029<\/mark>","fid":"content-d1e5464"},{"form":"029","weight":"1","pos":16,"context":"<mark>029<\/mark>","fid":"content-d1e5464"}]},{"docId":"gruber-josef","docUri":"gruber-josef.html","score":1,"contexts":[{"form":"029","weight":"1","pos":106,"context":"...aut. score of a Missa Solemnis (WAB <mark>029<\/mark>) signed “Josef Gruber | Stiftsorganist. | St....","fid":"content-d1e24955"}]},{"docId":"anonymus-102","docUri":"anonymus-102.html","score":1,"contexts":[{"form":"029","weight":"1","pos":87,"context":" <mark>029<\/mark> ","fid":"editions-table"}]},{"docId":"anonymus-104","docUri":"anonymus-104.html","score":1,"contexts":[{"form":"029","weight":"1","pos":87,"context":" <mark>029<\/mark> ","fid":"editions-table"}]},{"docId":"anonymus-103","docUri":"anonymus-103.html","score":1,"contexts":[{"form":"029","weight":"1","pos":87,"context":" <mark>029<\/mark> ","fid":"editions-table"}]},{"docId":"Tabelle%202","docUri":"Tabelle%202.html","score":1,"contexts":[{"form":"029","weight":"1","pos":43,"context":"...Anonymus 022 Anonymus 023 Anonymus 027 Anonymus 028 Anonymus <mark>029<\/mark> Anonymus 030 Anonymus 031 Anonymus 032 Anonymus 033 Anonymus...","fid":"d9e85"}]},{"docId":"anonymus-101","docUri":"anonymus-101.html","score":1,"contexts":[{"form":"029","weight":"1","pos":87,"context":" <mark>029<\/mark> ","fid":"editions-table"}]},{"docId":"schimatschek-franz","docUri":"schimatschek-franz.html","score":1,"contexts":[{"form":"029","weight":"1","pos":107,"context":" <mark>029<\/mark> ","fid":"editions-table"}]},{"docId":"kopist-j-h","docUri":"kopist-j-h.html","score":1,"contexts":[{"form":"029","weight":"1","pos":479,"context":" <mark>029<\/mark> ","fid":"editions-table"}]},{"docId":"anonymus-105","docUri":"anonymus-105.html","score":1,"contexts":[{"form":"029","weight":"1","pos":87,"context":" <mark>029<\/mark> ","fid":"editions-table"}]}]}