{"stem":"045","instances":[{"docId":"toc","docUri":"toc.html","score":2,"contexts":[{"form":"045","weight":"1","pos":1204,"context":"Anonymus <mark>045<\/mark>","fid":"tocTable"},{"form":"045","weight":"1","pos":1206,"context":"anonymus-<mark>045<\/mark>.xml","fid":"tocTable"}]},{"docId":"auer-max","docUri":"auer-max.html","score":1,"contexts":[{"form":"045","weight":"1","pos":190,"context":" <mark>045<\/mark> ","fid":"editions-table"}]},{"docId":"anonymus-045","docUri":"anonymus-045.html","score":2,"contexts":[{"form":"045","weight":"2","pos":20,"context":"Anonymus <mark>045<\/mark>","fid":"content-d1e7216"}]},{"docId":"Tabelle_1","docUri":"Tabelle_1.html","score":1,"contexts":[{"form":"045","weight":"1","pos":69,"context":" Anonymus <mark>045<\/mark> ","fid":"page"}]},{"docId":"anonymus-111","docUri":"anonymus-111.html","score":1,"contexts":[{"form":"045","weight":"1","pos":81,"context":" <mark>045<\/mark> ","fid":"editions-table"}]}]}