{"stem":"108","instances":[{"docId":"anonymus-013","docUri":"anonymus-013.html","score":11,"contexts":[{"form":"108","weight":"1","pos":564,"context":" <mark>108<\/mark> ","fid":"editions-table"},{"form":"108","weight":"1","pos":581,"context":" <mark>108<\/mark> ","fid":"editions-table"},{"form":"108","weight":"1","pos":592,"context":" <mark>108<\/mark> ","fid":"editions-table"},{"form":"108","weight":"1","pos":604,"context":" <mark>108<\/mark> ","fid":"editions-table"},{"form":"108","weight":"1","pos":615,"context":" <mark>108<\/mark> ","fid":"editions-table"},{"form":"108","weight":"1","pos":629,"context":" <mark>108<\/mark> ","fid":"editions-table"},{"form":"108","weight":"1","pos":645,"context":" <mark>108<\/mark> ","fid":"editions-table"},{"form":"108","weight":"1","pos":665,"context":" <mark>108<\/mark> ","fid":"editions-table"},{"form":"108","weight":"1","pos":682,"context":" <mark>108<\/mark> ","fid":"editions-table"},{"form":"108","weight":"1","pos":691,"context":" <mark>108<\/mark> ","fid":"editions-table"},{"form":"108","weight":"1","pos":702,"context":" <mark>108<\/mark> ","fid":"editions-table"}]},{"docId":"hofmeyr-leopold","docUri":"hofmeyr-leopold.html","score":7,"contexts":[{"form":"108","weight":"1","pos":99,"context":" <mark>108<\/mark> ","fid":"editions-table"},{"form":"108","weight":"1","pos":116,"context":" <mark>108<\/mark> ","fid":"editions-table"},{"form":"108","weight":"1","pos":131,"context":" <mark>108<\/mark> ","fid":"editions-table"},{"form":"108","weight":"1","pos":146,"context":" <mark>108<\/mark> ","fid":"editions-table"},{"form":"108","weight":"1","pos":170,"context":" <mark>108<\/mark> ","fid":"editions-table"},{"form":"108","weight":"1","pos":186,"context":" <mark>108<\/mark> ","fid":"editions-table"},{"form":"108","weight":"1","pos":195,"context":" <mark>108<\/mark> ","fid":"editions-table"}]},{"docId":"aigner-karl","docUri":"aigner-karl.html","score":4,"contexts":[{"form":"108","weight":"1","pos":209,"context":" <mark>108<\/mark> ","fid":"editions-table"},{"form":"108","weight":"1","pos":227,"context":" <mark>108<\/mark> ","fid":"editions-table"},{"form":"108","weight":"1","pos":239,"context":" <mark>108<\/mark> ","fid":"editions-table"},{"form":"108","weight":"1","pos":258,"context":" <mark>108<\/mark> ","fid":"editions-table"}]},{"docId":"anonymus-108","docUri":"anonymus-108.html","score":4,"contexts":[{"form":"108","weight":"2","pos":20,"context":"Anonymus <mark>108<\/mark>","fid":"content-d1e15326"},{"form":"108","weight":"1","pos":32,"context":" Der Kopist Anonymus <mark>108<\/mark> präparierte für Bruckner einen Partiturbogen, der bei der...","fid":"content-d1e15326"},{"form":"108","weight":"1","pos":43,"context":" Anonymus <mark>108<\/mark> prepared a bifolio for Bruckner’s sketches for Helgoland....","fid":"content-d1e15326"}]},{"docId":"noll-johann","docUri":"noll-johann.html","score":3,"contexts":[{"form":"108","weight":"1","pos":328,"context":"...40r–45r; 49r–54r; 58r–63r; 67r–72r; 76r–81r; 85r–90r; 94r–98v; 103r–<mark>108<\/mark>r; 112r–117r; 121r–125v;...","fid":"editions-table"},{"form":"108","weight":"1","pos":387,"context":"106v–<mark>108<\/mark>r","fid":"editions-table"},{"form":"108","weight":"1","pos":388,"context":"<mark>108<\/mark>r","fid":"editions-table"}]},{"docId":"toc","docUri":"toc.html","score":2,"contexts":[{"form":"108","weight":"1","pos":1000,"context":"Anonymus <mark>108<\/mark>","fid":"tocTable"},{"form":"108","weight":"1","pos":1002,"context":"anonymus-<mark>108<\/mark>.xml","fid":"tocTable"}]},{"docId":"christ-viktor","docUri":"christ-viktor.html","score":2,"contexts":[{"form":"108","weight":"1","pos":106,"context":" <mark>108<\/mark> ","fid":"editions-table"},{"form":"108","weight":"1","pos":119,"context":" <mark>108<\/mark> ","fid":"editions-table"}]},{"docId":"anonymus-072","docUri":"anonymus-072.html","score":2,"contexts":[{"form":"108","weight":"1","pos":227,"context":" <mark>108<\/mark> ","fid":"editions-table"},{"form":"108","weight":"1","pos":241,"context":" <mark>108<\/mark> ","fid":"editions-table"}]},{"docId":"schalk-josef","docUri":"schalk-josef.html","score":2,"contexts":[{"form":"108","weight":"1","pos":152,"context":" <mark>108<\/mark> ","fid":"editions-table"},{"form":"108","weight":"1","pos":165,"context":" <mark>108<\/mark> ","fid":"editions-table"}]},{"docId":"anonymus-016","docUri":"anonymus-016.html","score":2,"contexts":[{"form":"108","weight":"1","pos":347,"context":" <mark>108<\/mark> ","fid":"editions-table"},{"form":"108","weight":"1","pos":362,"context":" <mark>108<\/mark> ","fid":"editions-table"}]},{"docId":"kopist-j-h","docUri":"kopist-j-h.html","score":2,"contexts":[{"form":"108","weight":"1","pos":760,"context":" <mark>108<\/mark> ","fid":"editions-table"},{"form":"108","weight":"1","pos":771,"context":" <mark>108<\/mark> ","fid":"editions-table"}]},{"docId":"anonymus-073","docUri":"anonymus-073.html","score":2,"contexts":[{"form":"108","weight":"1","pos":208,"context":" <mark>108<\/mark> ","fid":"editions-table"},{"form":"108","weight":"1","pos":232,"context":" <mark>108<\/mark> ","fid":"editions-table"}]},{"docId":"schalk-franz","docUri":"schalk-franz.html","score":1,"contexts":[{"form":"108","weight":"1","pos":104,"context":" <mark>108<\/mark> ","fid":"editions-table"}]},{"docId":"anonymus-074","docUri":"anonymus-074.html","score":1,"contexts":[{"form":"108","weight":"1","pos":209,"context":" <mark>108<\/mark> ","fid":"editions-table"}]},{"docId":"Tabelle_1","docUri":"Tabelle_1.html","score":1,"contexts":[{"form":"108","weight":"1","pos":129,"context":" Anonymus <mark>108<\/mark> ","fid":"page"}]},{"docId":"paur-karl","docUri":"paur-karl.html","score":1,"contexts":[{"form":"108","weight":"1","pos":170,"context":" <mark>108<\/mark> ","fid":"editions-table"}]},{"docId":"anonymus-075","docUri":"anonymus-075.html","score":1,"contexts":[{"form":"108","weight":"1","pos":208,"context":" <mark>108<\/mark> ","fid":"editions-table"}]},{"docId":"schimatschek-franz","docUri":"schimatschek-franz.html","score":1,"contexts":[{"form":"108","weight":"1","pos":620,"context":"...14); 89r–96r (Ten 2, St. 18); 101r–<mark>108<\/mark>r (Ten 2, St. 19); 109r–116...","fid":"editions-table"}]}]}