{"stem":"118","instances":[{"docId":"anonymus-118","docUri":"anonymus-118.html","score":6,"contexts":[{"form":"118","weight":"2","pos":14,"context":"Anonymus <mark>118<\/mark>","fid":"page"},{"form":"118","weight":"1","pos":16,"context":" Anonymus <mark>118<\/mark> 118 St. Florian St. Florianer Kopisten St. Florian copyist...","fid":"d125e86"},{"form":"118","weight":"1","pos":17,"context":" Anonymus 118 <mark>118<\/mark> St. Florian St. Florianer Kopisten St. Florian copyist Sekundärquellen...","fid":"d125e86"},{"form":"118","weight":"1","pos":29,"context":" Die Kopisten Anonymus 117–<mark>118<\/mark>, Anonymus 121–124 sowie Anonymus 127–...","fid":"d125e118"},{"form":"118","weight":"1","pos":51,"context":" Anonymus 117–<mark>118<\/mark>, Anonymus 121–124, Anonymus 127–...","fid":"d125e128"}]},{"docId":"kopist-m-sch","docUri":"kopist-m-sch.html","score":3,"contexts":[{"form":"118","weight":"1","pos":109,"context":"...9v zwischen 1848 und 14.03.1849 A-KR-E5-<mark>118<\/mark> Requiem 039 Partitur 1r–36v; 38r–65v 65v Beispiele entnommen aus:...","fid":"d205e86"},{"form":"118","weight":"1","pos":116,"context":"...Partitur 1r–36v; 38r–65v 65v Beispiele entnommen aus: A-KR-E5-<mark>118<\/mark> Examples taken from: A-KR-E5-118 Notenschlüssel Clefs...","fid":"d205e86"},{"form":"118","weight":"1","pos":121,"context":"...A-KR-E5-118 Examples taken from: A-KR-E5-<mark>118<\/mark> Notenschlüssel Clefs Akzidentien Accidentals Taktvorzeichnung Time Signatures Pausen Rests...","fid":"d205e86"}]},{"docId":"anonymus-121","docUri":"anonymus-121.html","score":2,"contexts":[{"form":"118","weight":"1","pos":29,"context":" Die Kopisten Anonymus 117–<mark>118<\/mark>, Anonymus 121–124 sowie Anonymus 127–...","fid":"d128e118"},{"form":"118","weight":"1","pos":51,"context":" Anonymus 117–<mark>118<\/mark>, Anonymus 121–124, Anonymus 127–...","fid":"d128e128"}]},{"docId":"anonymus-130","docUri":"anonymus-130.html","score":2,"contexts":[{"form":"118","weight":"1","pos":29,"context":" Die Kopisten Anonymus 117–<mark>118<\/mark>, Anonymus 121–124 sowie Anonymus 127–...","fid":"d137e118"},{"form":"118","weight":"1","pos":51,"context":" Anonymus 117–<mark>118<\/mark>, Anonymus 121–124, Anonymus 127–...","fid":"d137e128"}]},{"docId":"anonymus-129","docUri":"anonymus-129.html","score":2,"contexts":[{"form":"118","weight":"1","pos":29,"context":" Die Kopisten Anonymus 117–<mark>118<\/mark>, Anonymus 121–124 sowie Anonymus 127–...","fid":"d136e118"},{"form":"118","weight":"1","pos":51,"context":" Anonymus 117–<mark>118<\/mark>, Anonymus 121–124, Anonymus 127–...","fid":"d136e128"}]},{"docId":"anonymus-128","docUri":"anonymus-128.html","score":2,"contexts":[{"form":"118","weight":"1","pos":29,"context":" Die Kopisten Anonymus 117–<mark>118<\/mark>, Anonymus 121–124 sowie Anonymus 127–...","fid":"d135e118"},{"form":"118","weight":"1","pos":51,"context":" Anonymus 117–<mark>118<\/mark>, Anonymus 121–124, Anonymus 127–...","fid":"d135e128"}]},{"docId":"anonymus-122","docUri":"anonymus-122.html","score":2,"contexts":[{"form":"118","weight":"1","pos":29,"context":" Die Kopisten Anonymus 117–<mark>118<\/mark>, Anonymus 121–124 sowie Anonymus 127–...","fid":"d129e118"},{"form":"118","weight":"1","pos":51,"context":" Anonymus 117–<mark>118<\/mark>, Anonymus 121–124, Anonymus 127–...","fid":"d129e128"}]},{"docId":"anonymus-131","docUri":"anonymus-131.html","score":2,"contexts":[{"form":"118","weight":"1","pos":29,"context":" Die Kopisten Anonymus 117–<mark>118<\/mark>, Anonymus 121–124 sowie Anonymus 127–...","fid":"d138e118"},{"form":"118","weight":"1","pos":51,"context":" Anonymus 117–<mark>118<\/mark>, Anonymus 121–124, Anonymus 127–...","fid":"d138e128"}]},{"docId":"anonymus-124","docUri":"anonymus-124.html","score":2,"contexts":[{"form":"118","weight":"1","pos":29,"context":" Die Kopisten Anonymus 117–<mark>118<\/mark>, Anonymus 121–124 sowie Anonymus 127–...","fid":"d131e118"},{"form":"118","weight":"1","pos":51,"context":" Anonymus 117–<mark>118<\/mark>, Anonymus 121–124, Anonymus 127–...","fid":"d131e128"}]},{"docId":"anonymus-123","docUri":"anonymus-123.html","score":2,"contexts":[{"form":"118","weight":"1","pos":29,"context":" Die Kopisten Anonymus 117–<mark>118<\/mark>, Anonymus 121–124 sowie Anonymus 127–...","fid":"d130e118"},{"form":"118","weight":"1","pos":51,"context":" Anonymus 117–<mark>118<\/mark>, Anonymus 121–124, Anonymus 127–...","fid":"d130e128"}]},{"docId":"toc","docUri":"toc.html","score":2,"contexts":[{"form":"118","weight":"1","pos":535,"context":"Anonymus <mark>118<\/mark>","fid":"tocTable"},{"form":"118","weight":"1","pos":537,"context":"anonymus-<mark>118<\/mark>.xml","fid":"tocTable"}]},{"docId":"anonymus-127","docUri":"anonymus-127.html","score":2,"contexts":[{"form":"118","weight":"1","pos":29,"context":" Die Kopisten Anonymus 117–<mark>118<\/mark>, Anonymus 121–124 sowie Anonymus 127–...","fid":"d134e118"},{"form":"118","weight":"1","pos":51,"context":" Anonymus 117–<mark>118<\/mark>, Anonymus 121–124, Anonymus 127–...","fid":"d134e128"}]},{"docId":"Tabelle%202","docUri":"Tabelle%202.html","score":1,"contexts":[{"form":"118","weight":"1","pos":135,"context":"...Anonymus 113 Anonymus 114 Anonymus 115 Anonymus 116 Anonymus <mark>118<\/mark> Anonymus 119 Anonymus 120 Anonymus 121 Anonymus 122 Anonymus...","fid":"d9e85"}]},{"docId":"Tabelle%203","docUri":"Tabelle%203.html","score":1,"contexts":[{"form":"118","weight":"1","pos":63,"context":"...Anonymus 102 Anonymus 103 Anonymus 104 Anonymus 105 Anonymus <mark>118<\/mark> Anonymus 121 Anonymus 122 Anonymus 123 Anonymus 124 Anonymus...","fid":"d11e85"}]},{"docId":"kopist-j-h","docUri":"kopist-j-h.html","score":1,"contexts":[{"form":"118","weight":"1","pos":711,"context":"...abgeschrieben 10.09.1868 A-WnMus.Hs.19687 Fantasie <mark>118<\/mark> Partitur 3r–4v 24.01.1869–12.09.1869...","fid":"d202e86"}]},{"docId":"schimatschek-franz","docUri":"schimatschek-franz.html","score":1,"contexts":[{"form":"118","weight":"1","pos":441,"context":"...91r–93v; 100r–102v; 109r–111v; <mark>118<\/mark>r–120v; 127r–129v; 136r–...","fid":"d230e86"}]},{"docId":"kellner-altman","docUri":"kellner-altman.html","score":1,"contexts":[{"form":"118","weight":"1","pos":81,"context":"...Date zwischen 1848 und 14.03.1849 A-KR-E5-<mark>118<\/mark> Requiem 039 Partitur 37r–37v [1854?] A-WnMus...","fid":"d193e86"}]}]}