{"stem":"144","instances":[{"docId":"anonymus-144","docUri":"anonymus-144.html","score":4,"contexts":[{"form":"144","weight":"2","pos":2,"context":"Anonymus <mark>144<\/mark>","fid":"content-d1e19687"},{"form":"144","weight":"1","pos":9,"context":" Die Partiturabschriften der Kopisten Anonymus 143, <mark>144<\/mark> und 145 dienten alle samt als Stichvorlagen für den...","fid":"content-d1e19687"},{"form":"144","weight":"1","pos":26,"context":" The scores of Anonymus 143, <mark>144<\/mark> and 145 served as the engraver’s copies for the...","fid":"content-d1e19687"}]},{"docId":"anonymus-143","docUri":"anonymus-143.html","score":2,"contexts":[{"form":"144","weight":"1","pos":9,"context":" Die Partiturabschriften der Kopisten Anonymus 143, <mark>144<\/mark> und 145 dienten alle samt als Stichvorlagen für den...","fid":"content-d1e19558"},{"form":"144","weight":"1","pos":26,"context":" The scores of Anonymus 143, <mark>144<\/mark> and 145 served as the engraver’s copies for the...","fid":"content-d1e19558"}]},{"docId":"anonymus-145","docUri":"anonymus-145.html","score":2,"contexts":[{"form":"144","weight":"1","pos":9,"context":" Die Partiturabschriften der Kopisten Anonymus 143, <mark>144<\/mark> und 145 dienten alle samt als Stichvorlagen für den...","fid":"content-d1e19816"},{"form":"144","weight":"1","pos":26,"context":" The scores of Anonymus 143, <mark>144<\/mark> and 145 served as the engraver’s copies for the...","fid":"content-d1e19816"}]}]}