{"stem":"198","instances":[{"docId":"kopist-e-m","docUri":"kopist-e-m.html","score":4,"contexts":[{"form":"198","weight":"1","pos":150,"context":"...Copyist’s Hand Copyist’s Signature or Date ca. 1846 A-KN<mark>198<\/mark>_4 Vier Tantum ergo 041 Stimmen 1r–4r 1v 1891...","fid":"d196e86"},{"form":"198","weight":"1","pos":157,"context":"...Vier Tantum ergo 041 Stimmen 1r–4r 1v 1891 A-KN<mark>198<\/mark>_3 Pange lingua 031 Stimmen 2r–9r 2r; 3r; 4r;...","fid":"d196e86"},{"form":"198","weight":"1","pos":165,"context":"...5r; 6r; 7r; 8r; 9r Beispiele entnommen aus: A-KN<mark>198<\/mark>_3 Examples taken from: A-KN198_3 Notenschlüssel...","fid":"d196e86"},{"form":"198","weight":"1","pos":170,"context":"...aus: A-KN198_3 Examples taken from: A-KN<mark>198<\/mark>_3 Notenschlüssel Clefs Akzidentien Accidentals Taktvorzeichnung Time Signatures Pausen...","fid":"d196e86"}]},{"docId":"anonymus-115","docUri":"anonymus-115.html","score":3,"contexts":[{"form":"198","weight":"1","pos":89,"context":"...the Copyist’s Hand Copyist’s Signature or Date 1891 A-KN<mark>198<\/mark>_3 Pange lingua 031 Partitur 1r Beispiele entnommen aus:...","fid":"d123e86"},{"form":"198","weight":"1","pos":97,"context":"...Pange lingua 031 Partitur 1r Beispiele entnommen aus: A-KN<mark>198<\/mark>_3 Examples taken from: A-KN198_3 Notenschlüssel...","fid":"d123e86"},{"form":"198","weight":"1","pos":102,"context":"...aus: A-KN198_3 Examples taken from: A-KN<mark>198<\/mark>_3 Notenschlüssel Clefs Akzidentien Accidentals Taktvorzeichnung Time Signatures Pausen...","fid":"d123e86"}]},{"docId":"schimatschek-franz","docUri":"schimatschek-franz.html","score":2,"contexts":[{"form":"198","weight":"1","pos":525,"context":"...186r (Bass 2, St. 6); 191r–<mark>198<\/mark>r (Bass 2, St. 7); 203r–210...","fid":"d230e86"},{"form":"198","weight":"1","pos":585,"context":"...r (Ten. 1, St. 5); 191r–<mark>198<\/mark>r (Ten. 1, St. 6); 199r–...","fid":"d230e86"}]},{"docId":"hlawaczek-franz","docUri":"hlawaczek-franz.html","score":1,"contexts":[{"form":"198","weight":"1","pos":391,"context":"...028 Stimmen 1869 1r–13v; 66r–78r; 133r–145r; <mark>198<\/mark>r–210r; 263r–271v; 277r–...","fid":"d187e86"}]},{"docId":"kopist-h-i","docUri":"kopist-h-i.html","score":1,"contexts":[{"form":"198","weight":"1","pos":155,"context":"...Copyist’s Hand Copyist’s Signature or Date ca. 1846 A-KN<mark>198<\/mark>_4 Vier Tantum ergo 041 Stimme (Sopran)...","fid":"d201e86"}]}]}