{"stem":"2121","instances":[{"docId":"Anonymus%20040","docUri":"Anonymus%20040.html","score":3,"contexts":[{"form":"2121","weight":"1","pos":64,"context":"...Signature or Date 07.06.1866 A-WnMus.Hs.<mark>2121<\/mark> Abendklänge 110 Klavierauszug 1v; 4r Beispiele entnommen aus: A-...","fid":"d48e86"},{"form":"2121","weight":"1","pos":72,"context":"...Klavierauszug 1v; 4r Beispiele entnommen aus: A-WnMus.Hs.<mark>2121<\/mark> Examples taken from: A-WnMus.Hs.2121 Notenschlüssel...","fid":"d48e86"},{"form":"2121","weight":"1","pos":78,"context":"....Hs.2121 Examples taken from: A-WnMus.Hs.<mark>2121<\/mark> Notenschlüssel Clefs Akzidentien Accidentals Taktvorzeichnung Time Signatures Pausen Rests...","fid":"d48e86"}]}]}