{"stem":"2233","instances":[{"docId":"anonymus-142","docUri":"anonymus-142.html","score":5,"contexts":[{"form":"2233","weight":"2","pos":100,"context":"Beispiele entnommen aus: A-WnPhA-<mark>2233<\/mark>-P | Examples taken from: A-WnPhA-...","fid":"content-d1e19422"},{"form":"2233","weight":"2","pos":106,"context":"...-P | Examples taken from: A-WnPhA-<mark>2233<\/mark>-P ","fid":"content-d1e19422"},{"form":"2233","weight":"1","pos":80,"context":"A-WnPhA<mark>2233<\/mark>-P","fid":"editions-table"}]}]}