{"stem":"478","instances":[{"docId":"Hofmeister,%20Karl","docUri":"Hofmeister,%20Karl.html","score":3,"contexts":[{"form":"478","weight":"1","pos":126,"context":"...Copyist’s Signature or Date 25.11.1866 A-LId<mark>478<\/mark>_7_29 Messe in e-Moll 027 Stimmen Bass 1...","fid":"d188e86"},{"form":"478","weight":"1","pos":145,"context":"...2. Fassung der Messe Beispiele entnommen aus: A-LId<mark>478<\/mark>_7_29 Examples taken from: A-LId478_7_29...","fid":"d188e86"},{"form":"478","weight":"1","pos":151,"context":"...LId478_7_29 Examples taken from: A-LId<mark>478<\/mark>_7_29 Notenschlüssel Clefs Akzidentien Accidentals Taktvorzeichnung Time Signatures Pausen...","fid":"d188e86"}]},{"docId":"Anonymus%20155","docUri":"Anonymus%20155.html","score":3,"contexts":[{"form":"478","weight":"1","pos":154,"context":"...Copyist’s Signature or Date 25.11.1866 A-LId<mark>478<\/mark>_7_29 Messe in e-Moll 027 Stimmen 1869 25r–32r...","fid":"d162e86"},{"form":"478","weight":"1","pos":174,"context":"...1. Fassung der Messe Beispiele entnommen aus: A-LId<mark>478<\/mark>_7_29 Examples taken from: A-LId478_7_29...","fid":"d162e86"},{"form":"478","weight":"1","pos":180,"context":"...LId478_7_29 Examples taken from: A-LId<mark>478<\/mark>_7_29 Notenschlüssel Clefs Akzidentien Accidentals Taktvorzeichnung Time Signatures Pausen...","fid":"d162e86"}]},{"docId":"Anonymus%20158","docUri":"Anonymus%20158.html","score":2,"contexts":[{"form":"478","weight":"1","pos":103,"context":"...ergo 041 Stimme 7r Beispiele entnommen aus: A-LId<mark>478<\/mark>_7_29 Examples taken from: A-LId478_7_29...","fid":"d165e86"},{"form":"478","weight":"1","pos":109,"context":"...LId478_7_29 Examples taken from: A-LId<mark>478<\/mark>_7_29 Notenschlüssel Clefs Akzidentien Accidentals Taktvorzeichnung Time Signatures Pausen...","fid":"d165e86"}]},{"docId":"Anonymus%20021","docUri":"Anonymus%20021.html","score":2,"contexts":[{"form":"478","weight":"1","pos":206,"context":".... 1 Stimme 11 25.11.1866 A-LId<mark>478<\/mark>_7_29 Messe in e-Moll 027 Stimmen Ten 2...","fid":"d29e86"},{"form":"478","weight":"1","pos":359,"context":"...St. 20, Cadd) 25.11.1866 A-LId<mark>478<\/mark>_7_29 Messe in e-Moll 027 Stimmen 9r–12v (...","fid":"d29e86"}]},{"docId":"Anonymus%20156","docUri":"Anonymus%20156.html","score":2,"contexts":[{"form":"478","weight":"1","pos":103,"context":"...Aequale 114 Stimmen 2r–4r Beispiele entnommen aus: A-LId<mark>478<\/mark>_7_29 Examples taken from: A-LId478_7_29...","fid":"d163e86"},{"form":"478","weight":"1","pos":109,"context":"...LId478_7_29 Examples taken from: A-LId<mark>478<\/mark>_7_29 Notenschlüssel Clefs Akzidentien Accidentals Taktvorzeichnung Time Signatures Pausen...","fid":"d163e86"}]},{"docId":"Anonymus%20157","docUri":"Anonymus%20157.html","score":2,"contexts":[{"form":"478","weight":"1","pos":104,"context":"...Stimme Fol. 7r Beispiele entnommen aus: A-LId<mark>478<\/mark>_7_29 Examples taken from: A-LId478_7_29...","fid":"d164e86"},{"form":"478","weight":"1","pos":110,"context":"...LId478_7_29 Examples taken from: A-LId<mark>478<\/mark>_7_29 Notenschlüssel Clefs Akzidentien Accidentals Taktvorzeichnung Time Signatures Pausen...","fid":"d164e86"}]},{"docId":"Anonymus%20009","docUri":"Anonymus%20009.html","score":1,"contexts":[{"form":"478","weight":"1","pos":277,"context":"...7, T3–L 10; 468v; 474r, Z. 1–4; <mark>478<\/mark>r, Z. 1–4; 480r; 485r, Z. 4–7;...","fid":"d17e86"}]},{"docId":"Carda,%20Johann","docUri":"Carda,%20Johann.html","score":1,"contexts":[{"form":"478","weight":"1","pos":606,"context":"...r–473v; 474r, Z. 5–477v; <mark>478<\/mark>r, Z. 6–479v; 481r–485r,...","fid":"d176e86"}]},{"docId":"Schimatschek,%20Franz","docUri":"Schimatschek,%20Franz.html","score":1,"contexts":[{"form":"478","weight":"1","pos":627,"context":"...are not foliated. 25.11.1866 A-LId<mark>478<\/mark>_7_29 Messe in e-Moll 027 Stimmen 1r–8r (...","fid":"d230e86"}]}]}