{"stem":"503","instances":[{"docId":"carda-johann","docUri":"carda-johann.html","score":2,"contexts":[{"form":"503","weight":"1","pos":478,"context":"...2; 497v, Z. 10–498v; 500r–<mark>503<\/mark>r; 503v, Z. 5–508r, Z. 10,...","fid":"editions-table"},{"form":"503","weight":"1","pos":479,"context":"...v, Z. 10–498v; 500r–503r; <mark>503<\/mark>v, Z. 5–508r, Z. 10, T2; 508...","fid":"editions-table"}]},{"docId":"anonymus-009","docUri":"anonymus-009.html","score":1,"contexts":[{"form":"503","weight":"1","pos":216,"context":"...Z. 8, T 2,–Z. 9; 498r–498v; <mark>503<\/mark>v, Z. 1–4; 508r, Z. 10, T 3–7;...","fid":"editions-table"}]}]}