{"stem":"ablo","instances":[{"docId":"laska-josef","docUri":"laska-josef.html","score":3,"contexts":[{"form":"ABLO","weight":"1","pos":30,"context":"...Eine detaillierte Biographie findet sich im entsprechenden Artikel des <mark>ABLO<\/mark>: siehe ABLO ","fid":"d208e130"},{"form":"ABLO","weight":"1","pos":32,"context":"...findet sich im entsprechenden Artikel des ABLO: siehe <mark>ABLO<\/mark> ","fid":"d208e130"},{"form":"ABLO","weight":"1","pos":89,"context":"...vollständig abgeschrieben Have not seen. The Laska in <mark>ABLO<\/mark> is to young to have copied something with aut...","fid":"d208e86"}]},{"docId":"seiberl-josef","docUri":"seiberl-josef.html","score":2,"contexts":[{"form":"ABLO","weight":"1","pos":90,"context":"...Eine detaillierte Biographie findet sich im entsprechenden Artikel des <mark>ABLO<\/mark>: siehe ABLO ","fid":"d233e160"},{"form":"ABLO","weight":"1","pos":92,"context":"...findet sich im entsprechenden Artikel des ABLO: siehe <mark>ABLO<\/mark> ","fid":"d233e160"}]},{"docId":"graflinger-franz","docUri":"graflinger-franz.html","score":2,"contexts":[{"form":"ABLO","weight":"1","pos":65,"context":"...Eine detaillierte Biographie findet sich im entsprechenden Artikel des <mark>ABLO<\/mark>: siehe ABLO ","fid":"d184e136"},{"form":"ABLO","weight":"1","pos":67,"context":"...findet sich im entsprechenden Artikel des ABLO: siehe <mark>ABLO<\/mark> ","fid":"d184e136"}]},{"docId":"burkhart-franz","docUri":"burkhart-franz.html","score":2,"contexts":[{"form":"ABLO","weight":"1","pos":30,"context":"...Eine detaillierte Biographie findet sich im entsprechenden Artikel des <mark>ABLO<\/mark>: siehe ABLO ","fid":"d175e128"},{"form":"ABLO","weight":"1","pos":32,"context":"...findet sich im entsprechenden Artikel des ABLO: siehe <mark>ABLO<\/mark> ","fid":"d175e128"}]},{"docId":"loidol-oddo","docUri":"loidol-oddo.html","score":2,"contexts":[{"form":"ABLO","weight":"1","pos":37,"context":"...Eine detaillierte Biographie findet sich im entsprechenden Artikel des <mark>ABLO<\/mark>: siehe ABLO ","fid":"d210e136"},{"form":"ABLO","weight":"1","pos":39,"context":"...findet sich im entsprechenden Artikel des ABLO: siehe <mark>ABLO<\/mark> ","fid":"d210e136"}]},{"docId":"weinwurm-rudolf","docUri":"weinwurm-rudolf.html","score":2,"contexts":[{"form":"ABLO","weight":"1","pos":33,"context":"...Eine detaillierte Biographie findet sich im entsprechenden Artikel des <mark>ABLO<\/mark>: siehe ABLO ","fid":"d239e136"},{"form":"ABLO","weight":"1","pos":35,"context":"...findet sich im entsprechenden Artikel des ABLO: siehe <mark>ABLO<\/mark> ","fid":"d239e136"}]},{"docId":"lowe-ferdinand","docUri":"lowe-ferdinand.html","score":2,"contexts":[{"form":"ABLO","weight":"1","pos":34,"context":"...Eine detaillierte Biographie findet sich im entsprechenden Artikel des <mark>ABLO<\/mark>: siehe ABLO ","fid":"d211e136"},{"form":"ABLO","weight":"1","pos":36,"context":"...findet sich im entsprechenden Artikel des ABLO: siehe <mark>ABLO<\/mark> ","fid":"d211e136"}]},{"docId":"schalk-josef","docUri":"schalk-josef.html","score":2,"contexts":[{"form":"ABLO","weight":"1","pos":34,"context":"...Eine detaillierte Biographie findet sich im entsprechenden Artikel des <mark>ABLO<\/mark>: siehe ABLO ","fid":"d229e136"},{"form":"ABLO","weight":"1","pos":36,"context":"...findet sich im entsprechenden Artikel des ABLO: siehe <mark>ABLO<\/mark> ","fid":"d229e136"}]},{"docId":"meissner-anton","docUri":"meissner-anton.html","score":2,"contexts":[{"form":"ABLO","weight":"1","pos":29,"context":"...Eine detaillierte Biographie findet sich im entsprechenden Artikel des <mark>ABLO<\/mark>: siehe ABLO ","fid":"d213e129"},{"form":"ABLO","weight":"1","pos":31,"context":"...findet sich im entsprechenden Artikel des ABLO: siehe <mark>ABLO<\/mark> ","fid":"d213e129"}]},{"docId":"auer-max","docUri":"auer-max.html","score":2,"contexts":[{"form":"ABLO","weight":"1","pos":31,"context":"...Eine detaillierte Biographie findet sich im entsprechenden Artikel des <mark>ABLO<\/mark>: siehe ABLO ","fid":"d169e128"},{"form":"ABLO","weight":"1","pos":33,"context":"...findet sich im entsprechenden Artikel des ABLO: siehe <mark>ABLO<\/mark> ","fid":"d169e128"}]},{"docId":"stradal-august","docUri":"stradal-august.html","score":2,"contexts":[{"form":"ABLO","weight":"1","pos":34,"context":"...Eine detaillierte Biographie findet sich im entsprechenden Artikel des <mark>ABLO<\/mark>: siehe ABLO ","fid":"d235e136"},{"form":"ABLO","weight":"1","pos":36,"context":"...findet sich im entsprechenden Artikel des ABLO: siehe <mark>ABLO<\/mark> ","fid":"d235e136"}]},{"docId":"hofmeyr-leopold","docUri":"hofmeyr-leopold.html","score":2,"contexts":[{"form":"ABLO","weight":"1","pos":31,"context":"...Eine detaillierte Biographie findet sich im entsprechenden Artikel des <mark>ABLO<\/mark>: siehe ABLO ","fid":"d189e132"},{"form":"ABLO","weight":"1","pos":33,"context":"...findet sich im entsprechenden Artikel des ABLO: siehe <mark>ABLO<\/mark> ","fid":"d189e132"}]},{"docId":"hlawaczek-franz","docUri":"hlawaczek-franz.html","score":2,"contexts":[{"form":"ABLO","weight":"1","pos":316,"context":"...Eine detaillierte Biographie findet sich im entsprechenden Artikel des <mark>ABLO<\/mark>: siehe ABLO ","fid":"d187e176"},{"form":"ABLO","weight":"1","pos":318,"context":"...findet sich im entsprechenden Artikel des ABLO: siehe <mark>ABLO<\/mark> ","fid":"d187e176"}]},{"docId":"gollerich-august","docUri":"gollerich-august.html","score":2,"contexts":[{"form":"ABLO","weight":"1","pos":35,"context":"...Eine detaillierte Biographie findet sich im entsprechenden Artikel des <mark>ABLO<\/mark>: siehe ABLO ","fid":"d183e136"},{"form":"ABLO","weight":"1","pos":37,"context":"...findet sich im entsprechenden Artikel des ABLO: siehe <mark>ABLO<\/mark> ","fid":"d183e136"}]},{"docId":"rott-hans","docUri":"rott-hans.html","score":2,"contexts":[{"form":"ABLO","weight":"1","pos":31,"context":"...Eine detaillierte Biographie findet sich im entsprechenden Artikel des <mark>ABLO<\/mark>: siehe ABLO ","fid":"d227e133"},{"form":"ABLO","weight":"1","pos":33,"context":"...findet sich im entsprechenden Artikel des ABLO: siehe <mark>ABLO<\/mark> ","fid":"d227e133"}]},{"docId":"bayer-franz-xaver","docUri":"bayer-franz-xaver.html","score":2,"contexts":[{"form":"ABLO","weight":"1","pos":48,"context":"...Eine detaillierte Biographie findet sich im entsprechenden Artikel des <mark>ABLO<\/mark>: siehe ABLO ","fid":"d171e145"},{"form":"ABLO","weight":"1","pos":50,"context":"...findet sich im entsprechenden Artikel des ABLO: siehe <mark>ABLO<\/mark> ","fid":"d171e145"}]},{"docId":"christ-viktor","docUri":"christ-viktor.html","score":2,"contexts":[{"form":"ABLO","weight":"1","pos":31,"context":"...Eine detaillierte Biographie findet sich im entsprechenden Artikel des <mark>ABLO<\/mark>: siehe ABLO ","fid":"d177e130"},{"form":"ABLO","weight":"1","pos":33,"context":"...findet sich im entsprechenden Artikel des ABLO: siehe <mark>ABLO<\/mark> ","fid":"d177e130"}]},{"docId":"schalk-franz","docUri":"schalk-franz.html","score":2,"contexts":[{"form":"ABLO","weight":"1","pos":32,"context":"...Eine detaillierte Biographie findet sich im entsprechenden Artikel des <mark>ABLO<\/mark>: siehe ABLO ","fid":"d228e133"},{"form":"ABLO","weight":"1","pos":34,"context":"...findet sich im entsprechenden Artikel des ABLO: siehe <mark>ABLO<\/mark> ","fid":"d228e133"}]},{"docId":"schimatschek-franz","docUri":"schimatschek-franz.html","score":2,"contexts":[{"form":"ABLO","weight":"1","pos":48,"context":"...Eine detaillierte Biographie findet sich im entsprechenden Artikel des <mark>ABLO<\/mark>: siehe ABLO ","fid":"d230e147"},{"form":"ABLO","weight":"1","pos":50,"context":"...findet sich im entsprechenden Artikel des ABLO: siehe <mark>ABLO<\/mark> ","fid":"d230e147"}]},{"docId":"kremser-eduard","docUri":"kremser-eduard.html","score":2,"contexts":[{"form":"ABLO","weight":"1","pos":30,"context":"...Eine detaillierte Biographie findet sich im entsprechenden Artikel des <mark>ABLO<\/mark>: siehe ABLO ","fid":"d207e130"},{"form":"ABLO","weight":"1","pos":32,"context":"...findet sich im entsprechenden Artikel des ABLO: siehe <mark>ABLO<\/mark> ","fid":"d207e130"}]},{"docId":"muller-franz-xaver","docUri":"muller-franz-xaver.html","score":2,"contexts":[{"form":"ABLO","weight":"1","pos":73,"context":"...Eine detaillierte Biographie findet sich im entsprechenden Artikel des <mark>ABLO<\/mark>: siehe ABLO ","fid":"d214e141"},{"form":"ABLO","weight":"1","pos":75,"context":"...findet sich im entsprechenden Artikel des ABLO: siehe <mark>ABLO<\/mark> ","fid":"d214e141"}]},{"docId":"hynais-cyrill","docUri":"hynais-cyrill.html","score":2,"contexts":[{"form":"ABLO","weight":"1","pos":74,"context":"...Eine detaillierte Biographie findet sich im entsprechenden Artikel des <mark>ABLO<\/mark>: siehe ABLO ","fid":"d190e139"},{"form":"ABLO","weight":"1","pos":76,"context":"...findet sich im entsprechenden Artikel des ABLO: siehe <mark>ABLO<\/mark> ","fid":"d190e139"}]},{"docId":"traumihler-ignaz","docUri":"traumihler-ignaz.html","score":2,"contexts":[{"form":"ABLO","weight":"1","pos":92,"context":"...Eine detaillierte Biographie findet sich im entsprechenden Artikel des <mark>ABLO<\/mark>: siehe ABLO ","fid":"d237e160"},{"form":"ABLO","weight":"1","pos":94,"context":"...findet sich im entsprechenden Artikel des ABLO: siehe <mark>ABLO<\/mark> ","fid":"d237e160"}]},{"docId":"burgstaller-johann-baptist","docUri":"burgstaller-johann-baptist.html","score":2,"contexts":[{"form":"ABLO","weight":"1","pos":34,"context":"...Eine detaillierte Biographie findet sich im entsprechenden Artikel des <mark>ABLO<\/mark>: siehe ABLO ","fid":"d174e127"},{"form":"ABLO","weight":"1","pos":36,"context":"...findet sich im entsprechenden Artikel des ABLO: siehe <mark>ABLO<\/mark> ","fid":"d174e127"}]},{"docId":"bayer-juliane","docUri":"bayer-juliane.html","score":2,"contexts":[{"form":"ABLO","weight":"1","pos":34,"context":"...Eine detaillierte Biographie findet sich im entsprechenden Artikel des <mark>ABLO<\/mark>: siehe ABLO ","fid":"d172e129"},{"form":"ABLO","weight":"1","pos":36,"context":"...findet sich im entsprechenden Artikel des ABLO: siehe <mark>ABLO<\/mark> ","fid":"d172e129"}]},{"docId":"aigner-karl","docUri":"aigner-karl.html","score":2,"contexts":[{"form":"ABLO","weight":"1","pos":44,"context":"...Eine detaillierte Biographie findet sich im entsprechenden Artikel des <mark>ABLO<\/mark>: siehe ABLO ","fid":"d7e132"},{"form":"ABLO","weight":"1","pos":46,"context":"...findet sich im entsprechenden Artikel des ABLO: siehe <mark>ABLO<\/mark> ","fid":"d7e132"}]},{"docId":"deubler-bernhard","docUri":"deubler-bernhard.html","score":2,"contexts":[{"form":"ABLO","weight":"1","pos":80,"context":"...Eine detaillierte Biographie findet sich im entsprechenden Artikel des <mark>ABLO<\/mark>: siehe ABLO ","fid":"d178e152"},{"form":"ABLO","weight":"1","pos":82,"context":"...findet sich im entsprechenden Artikel des ABLO: siehe <mark>ABLO<\/mark> ","fid":"d178e152"}]},{"docId":"eckstein-friedrich","docUri":"eckstein-friedrich.html","score":2,"contexts":[{"form":"ABLO","weight":"1","pos":83,"context":"...Eine detaillierte Biographie findet sich im entsprechenden Artikel des <mark>ABLO<\/mark>: siehe ABLO ","fid":"d179e148"},{"form":"ABLO","weight":"1","pos":85,"context":"...findet sich im entsprechenden Artikel des ABLO: siehe <mark>ABLO<\/mark> ","fid":"d179e148"}]},{"docId":"schmid-ernst-fritz","docUri":"schmid-ernst-fritz.html","score":1,"contexts":[{"form":"ABLO","weight":"1","pos":125,"context":"...im entsprechenden Artikel des Austria-Forum: siehe <mark>ABLO<\/mark> ","fid":"d231e142"}]}]}