{"stem":"base","instances":[{"docId":"berger-alfons","docUri":"berger-alfons.html","score":1,"contexts":[{"form":"based","weight":"1","pos":48,"context":"...and Frankenburg. The identification of Berger’s handwriting is <mark>based<\/mark> on the note in his copy of the Vier...","fid":"lang-en"}]},{"docId":"eckstein-friedrich","docUri":"eckstein-friedrich.html","score":1,"contexts":[{"form":"based","weight":"1","pos":33,"context":" The identification of his hand is <mark>based<\/mark> on a set of harmony exercises, which he...","fid":"lang-en"}]},{"docId":"anonymus-160","docUri":"anonymus-160.html","score":1,"contexts":[{"form":"based","weight":"1","pos":49,"context":"...be found. The identification of the hand is <mark>based<\/mark> on a photocopy in the Fonds of the Bruckner...","fid":"lang-en"}]},{"docId":"weinwurm-rudolf","docUri":"weinwurm-rudolf.html","score":1,"contexts":[{"form":"based","weight":"1","pos":49,"context":"...the hand of Bruckner’s lifelong friend Rudolf Weinwurm is <mark>based<\/mark> on the latter’s autograph score of his . The...","fid":"lang-en"}]},{"docId":"graflinger-franz","docUri":"graflinger-franz.html","score":1,"contexts":[{"form":"based","weight":"1","pos":27,"context":" The identification of his hand is <mark>based<\/mark> on the autograph score of his song “Mein Schatz”...","fid":"lang-en"}]}]}