{"stem":"complet","instances":[{"docId":"Anonymus%20071","docUri":"Anonymus%20071.html","score":1,"contexts":[{"form":"completed","weight":"1","pos":50,"context":"...prepared a manuscript of the Fifth Symphony after Bruckner <mark>completed<\/mark> his revisions of 1877-1878.","fid":"d79e129"}]},{"docId":"Stolz,%20Ernst","docUri":"Stolz,%20Ernst.html","score":1,"contexts":[{"form":"completed","weight":"1","pos":176,"context":"...in addition to the self-disclosure that Stolz <mark>completed<\/mark> the Primo (m. 1-17 of the Finale) and...","fid":"d234e173"}]},{"docId":"Anonymus%20126","docUri":"Anonymus%20126.html","score":1,"contexts":[{"form":"completed","weight":"1","pos":49,"context":"...manuscripts were prepared shortly after their works had been <mark>completed<\/mark>, they probably date from 1884 or shortly thereafter...","fid":"d133e126"}]},{"docId":"Anonymus%20016","docUri":"Anonymus%20016.html","score":1,"contexts":[{"form":"completed","weight":"1","pos":177,"context":"...011), probably shortly after the work had been <mark>completed<\/mark> in 1884. The copyist was also involved in...","fid":"d24e129"}]}]}