{"stem":"czorrda","instances":[{"docId":"carda-johann","docUri":"carda-johann.html","score":2,"contexts":[{"form":"Czorrda“","weight":"1","pos":101,"context":"...Josef Maria Kaiser bezog sich Bruckner auf einen „<mark>Czorrda“<\/mark>, der bei Kaiser wegen eines Titelblattes für das...","fid":"content-d1e23123"},{"form":"Czorrda","weight":"1","pos":279,"context":"...to the Linz artist , Bruckner referred to a <mark>Czorrda<\/mark> who was supposed to have been in touch about...","fid":"editions-table"}]}]}