{"stem":"engag","instances":[{"docId":"anonymus-003","docUri":"anonymus-003.html","score":1,"contexts":[{"form":"engaged","weight":"1","pos":139,"context":"...for the Magnificat and Psalm 114. That Bruckner <mark>engaged<\/mark> him in 1852 to copy these two works,...","fid":"content-d1e926"}]},{"docId":"kopist-j-h","docUri":"kopist-j-h.html","score":1,"contexts":[{"form":"engaged","weight":"1","pos":166,"context":"...– are dated 1904. He was almost certainly <mark>engaged<\/mark> by August Göllerich to prepare manuscripts as study scores...","fid":"content-d1e27682"}]}]}