{"stem":"father","instances":[{"docId":"jari-franz","docUri":"jari-franz.html","score":1,"contexts":[{"form":"Father","weight":"1","pos":146,"context":"...life and remained here as a monastery musician. <mark>Father<\/mark> Paul told me this and said he could play...","fid":"d191e146"}]},{"docId":"kerschbaum-maximilian","docUri":"kerschbaum-maximilian.html","score":1,"contexts":[{"form":"Father","weight":"1","pos":103,"context":"...668–669. The author is grateful to <mark>Father<\/mark> Altmann Kellner who identified Kerschbaum’s hand. ","fid":"d194e150"}]}]}