{"stem":"intermezzo","instances":[{"docId":"anonymus-025","docUri":"anonymus-025.html","score":3,"contexts":[{"form":"Intermezzo","weight":"1","pos":54,"context":"...eben dieses Jahr datierte. Auch der Stimmensatz zum <mark>Intermezzo<\/mark> des Streichquartetts könnte im Jahr 1881 entstanden sein. ","fid":"content-d1e5045"},{"form":"Intermezzo","weight":"1","pos":93,"context":"...fol. 56r). His parts for the <mark>Intermezzo<\/mark> for String Quartet may also date from that year...","fid":"content-d1e5045"},{"form":"Intermezzo","weight":"1","pos":141,"context":" <mark>Intermezzo<\/mark> ","fid":"editions-table"}]},{"docId":"anonymus-152","docUri":"anonymus-152.html","score":3,"contexts":[{"form":"Intermezzo“","weight":"1","pos":34,"context":"...Kopist Anonymus 152 fertigte eine frühe Partiturabschrift des „<mark>Intermezzo“<\/mark> (WAB 113) an.","fid":"content-d1e20715"},{"form":"“Intermezzo”","weight":"1","pos":45,"context":" Anonymus 152 prepared an early score for the <mark>“Intermezzo”<\/mark> (WAB 113) for String Quintet.","fid":"content-d1e20715"},{"form":"Intermezzo","weight":"1","pos":76,"context":" <mark>Intermezzo<\/mark> ","fid":"editions-table"}]},{"docId":"auer-max","docUri":"auer-max.html","score":1,"contexts":[{"form":"Intermezzo","weight":"1","pos":164,"context":" <mark>Intermezzo<\/mark> ","fid":"editions-table"}]},{"docId":"schalk-franz","docUri":"schalk-franz.html","score":1,"contexts":[{"form":"Intermezzo","weight":"1","pos":91,"context":" <mark>Intermezzo<\/mark> ","fid":"editions-table"}]}]}