{"stem":"mitternacht","instances":[{"docId":"anonymus-149","docUri":"anonymus-149.html","score":1,"contexts":[{"form":"Mitternacht","weight":"1","pos":53,"context":" Um <mark>Mitternacht<\/mark> ","fid":"editions-table"}]},{"docId":"anonymus-029","docUri":"anonymus-029.html","score":1,"contexts":[{"form":"Mitternacht","weight":"1","pos":52,"context":" Um <mark>Mitternacht<\/mark> ","fid":"editions-table"}]},{"docId":"schmidinger-cajetan","docUri":"schmidinger-cajetan.html","score":1,"contexts":[{"form":"Mitternacht","weight":"1","pos":140,"context":" <mark>Mitternacht<\/mark> ","fid":"editions-table"}]},{"docId":"schimatschek-franz","docUri":"schimatschek-franz.html","score":1,"contexts":[{"form":"Mitternacht","weight":"1","pos":249,"context":" Um <mark>Mitternacht<\/mark> ","fid":"editions-table"}]},{"docId":"kopist-j-h","docUri":"kopist-j-h.html","score":1,"contexts":[{"form":"Mitternacht","weight":"1","pos":561,"context":" Um <mark>Mitternacht<\/mark> ","fid":"editions-table"}]},{"docId":"anonymus-148","docUri":"anonymus-148.html","score":1,"contexts":[{"form":"Mitternacht","weight":"1","pos":60,"context":" Um <mark>Mitternacht<\/mark> ","fid":"editions-table"}]}]}