{"stem":"nachlassfond","instances":[{"docId":"Anonymus%20160","docUri":"Anonymus%20160.html","score":1,"contexts":[{"form":"Nachlassfond","weight":"1","pos":44,"context":"...Die Identifizierung der Hand basiert auf einer Fotokopie im <mark>Nachlassfond<\/mark> der Bruckner-Gesamtausgabe (A-WnF60.BRGA...","fid":"d167e118"}]},{"docId":"Anonymus%20161","docUri":"Anonymus%20161.html","score":1,"contexts":[{"form":"Nachlassfond","weight":"1","pos":35,"context":"...ist lediglich als Fotokopie zusammen mit einem Stimmensatz im <mark>Nachlassfond<\/mark> der Bruckner-Gesamtausgabe (A-WnF60.BRGA...","fid":"d168e118"}]}]}