{"stem":"oboist","instances":[{"docId":"Karmazin,%20Jaroslav","docUri":"Karmazin,%20Jaroslav.html","score":2,"contexts":[{"form":"Oboist","weight":"1","pos":34,"context":"...Unterschrift teilweise als „Karmathin“ fehlinterpretiert werden kann, war <mark>Oboist<\/mark>, Sänger und Direktor der Steyrer Bürgermusikkapelle.1 Eine...","fid":"d192e127"},{"form":"oboist","weight":"1","pos":116,"context":"..., whose signature partly looks like “Karmathin” was an <mark>oboist<\/mark>, singer and Director of the Steyr Bürgermusikkapelle.1...","fid":"d192e159"}]}]}