{"stem":"pianist","instances":[{"docId":"posch-emil","docUri":"posch-emil.html","score":2,"contexts":[{"form":"Pianist","weight":"1","pos":67,"context":"...der Liedertafel „Frohsinn“. Zudem begleitete Posch als <mark>Pianist<\/mark> bei zahlreichen Veranstaltungen und sorgte in Oberösterreich für die...","fid":"d225e130"},{"form":"pianist","weight":"1","pos":156,"context":"...“Frohsinn”. In addition, Posch accompanied as a <mark>pianist<\/mark> at numerous events and ensured the dissemination of Richard...","fid":"d225e149"}]}]}