{"stem":"respect","instances":[{"docId":"Anonymus%20068","docUri":"Anonymus%20068.html","score":1,"contexts":[{"form":"respective","weight":"1","pos":44,"context":"...be assigned to the copyist Anonymus 067. The <mark>respective<\/mark> copies are listed under this name. ","fid":"d76e119"}]},{"docId":"Anonymus%20144","docUri":"Anonymus%20144.html","score":1,"contexts":[{"form":"respective","weight":"1","pos":56,"context":"...the engraver’s copies for the first prints of their <mark>respective<\/mark> works in Göllerich-Auer.1 Göll.-A. 2\/2,...","fid":"d151e127"}]},{"docId":"Anonymus%20059","docUri":"Anonymus%20059.html","score":1,"contexts":[{"form":"respective","weight":"1","pos":44,"context":"...be assigned to the copyist Anonymus 024. The <mark>respective<\/mark> copies are listed under this name. ","fid":"d67e119"}]},{"docId":"imprint","docUri":"imprint.html","score":1,"contexts":[{"form":"respect","weight":"1","pos":94,"context":"...duty to support the sciences and humanities in every <mark>respect<\/mark>. As a learned society, the OEAW fosters...","fid":"page"}]},{"docId":"Anonymus%20143","docUri":"Anonymus%20143.html","score":1,"contexts":[{"form":"respective","weight":"1","pos":60,"context":"...the engraver’s copies for the first prints of their <mark>respective<\/mark> works in Göllerich-Auer.1 Göll.-A. 3\/2,...","fid":"d150e127"}]},{"docId":"Anonymus%20110","docUri":"Anonymus%20110.html","score":1,"contexts":[{"form":"respective","weight":"1","pos":49,"context":"...be assigned to the copyist Anonymus 024. The <mark>respective<\/mark> copies are listed under this name. ","fid":"d118e124"}]},{"docId":"Anonymus%20145","docUri":"Anonymus%20145.html","score":1,"contexts":[{"form":"respective","weight":"1","pos":56,"context":"...the engraver’s copies for the first prints of their <mark>respective<\/mark> works in Göllerich-Auer.1 Göll.-A. 2\/2,...","fid":"d152e127"}]},{"docId":"Anonymus%20073","docUri":"Anonymus%20073.html","score":1,"contexts":[{"form":"respectively","weight":"1","pos":238,"context":"...his two movements with Anonymous W13 and Viktor Christ <mark>respectively<\/mark>. Juni 1884–10.08.1887 A-Wgm...","fid":"d81e86"}]}]}