{"stem":"timothi","instances":[{"docId":"Anonymus%20010","docUri":"Anonymus%20010.html","score":2,"contexts":[{"form":"Timothy","weight":"1","pos":81,"context":"...F Minor, in: „Bruckner Studies“, hg. <mark>Timothy<\/mark> L. Jackson and Paul Hawkshaw. (Cambridge,...","fid":"d18e121"},{"form":"Timothy","weight":"1","pos":159,"context":"...in F Minor.” In Bruckner Studies, ed. <mark>Timothy<\/mark> L. Jackson and Paul Hawkshaw. (Cambridge,...","fid":"d18e132"}]},{"docId":"Anonymus%20009","docUri":"Anonymus%20009.html","score":2,"contexts":[{"form":"Timothy","weight":"1","pos":90,"context":"...F Minor, in: „Bruckner Studies“, hg. <mark>Timothy<\/mark> L. Jackson and Paul Hawkshaw. (Cambridge,...","fid":"d17e121"},{"form":"Timothy","weight":"1","pos":177,"context":"...in F Minor.” In Bruckner Studies, ed. <mark>Timothy<\/mark> L. Jackson and Paul Hawkshaw. (Cambridge,...","fid":"d17e134"}]}]}