{"stem":"tritting","instances":[{"docId":"trittinger-adolf","docUri":"trittinger-adolf.html","score":4,"contexts":[{"form":"Trittinger","weight":"2","pos":11,"context":"<mark>Trittinger<\/mark>, Adolf","fid":"content-d1e35859"},{"form":"Trittinger","weight":"1","pos":14,"context":"<mark>Trittinger<\/mark>, Adolf","fid":"content-d1e35859"},{"form":"Trittingers","weight":"1","pos":24,"context":" Leopold Nowak identifizierte <mark>Trittingers<\/mark> Handschrift auf fol. 2r der Partiturabschrift der Vertonung...","fid":"content-d1e35859"}]},{"docId":"toc","docUri":"toc.html","score":2,"contexts":[{"form":"Trittinger","weight":"1","pos":932,"context":"<mark>Trittinger<\/mark>, Adolf","fid":"tocTable"},{"form":"trittinger","weight":"1","pos":935,"context":"<mark>trittinger<\/mark>-adolf.xml","fid":"tocTable"}]},{"docId":"Tabelle%202","docUri":"Tabelle%202.html","score":1,"contexts":[{"form":"Trittinger","weight":"1","pos":273,"context":"...Stolz, Ernst Stradal, August Traumihler, Ignaz <mark>Trittinger<\/mark>, Adolf Weinwurm, Rudolf ","fid":"d9e85"}]}]}