{"stem":"wienbibliothek","instances":[{"docId":"weinwurm-rudolf","docUri":"weinwurm-rudolf.html","score":2,"contexts":[{"form":"Wienbibliothek","weight":"1","pos":16,"context":"...seiner Komposition . Die Handschrift der wird in derder <mark>Wienbibliothek<\/mark> im Rathaus (A-Wst MH-1945) verwahrt...","fid":"lang-de"},{"form":"Wienbibliothek","weight":"1","pos":55,"context":"...of his . The manuscript is kept in the <mark>Wienbibliothek<\/mark> im Rathaus (A-Wst MH-1945). Weinwurm...","fid":"lang-en"}]}]}